{
    "version": 1,
    "mission_id": "M-STAGE3-AUTONOMY",
    "mission_title": "Stage 3: Agent Autonomy — auto-mission selection, auto-ship, audit trail",
    "branch": "dev",
    "type": "feature",
    "started_at": "2026-03-09T05:08:20Z",
    "current_phase": "context",
    "suits_active": [],
    "phases": {
        "context": {
            "status": "in_progress",
            "started_at": "2026-03-09T05:08:20Z"
        },
        "suit": {
            "status": "pending"
        },
        "build": {
            "status": "pending"
        },
        "test": {
            "status": "pending"
        },
        "review": {
            "status": "pending"
        },
        "learn": {
            "status": "pending"
        },
        "ship": {
            "status": "pending"
        }
    },
    "suit_compliance": {}
}